{
  "@context": "http://iiif.io/api/presentation/3/context.json",
  "id": "https://makenziepeacock.github.io/NoBoundaries/annotations/interview-with-bebe-mille-2018-1-of-4--canvas-1-gesel-mason.json",
  "type": "AnnotationPage",
  "label": "Gesel Mason",
  "items": [
    {
      "@context": "http://www.w3.org/ns/anno.jsonld",
      "id": "interview-with-bebe-mille-2018-1-of-4--canvas-1-gesel-mason-annotation-0.json",
      "type": "Annotation",
      "motivation": [
        "supplementing",
        "commenting"
      ],
      "body": {
        "type": "TextualBody",
        "value": "One of the reasons I found myself interested in revisiting this was because I had a chance to do it again, a version of the No Boundaries Project in 2014. When I did it I was like, \" Oh, I think it's still really ... \" I was talking to the students, I taught a class, and it was so interesting to hear how the students were reacting to the work of the African American choreographers, were excited about seeing the work, and it was such a different conversation than what I was having when I was in my 20s.",
        "format": "text/plain",
        "purpose": "commenting"
      },
      "target": {
        "source": {
          "id": "https://makenziepeacock.github.io/NoBoundaries/interview-with-bebe-mille-2018-1-of-4-/canvas-1/canvas",
          "type": "Canvas",
          "partOf": [
            {
              "id": "https://makenziepeacock.github.io/NoBoundaries/interview-with-bebe-mille-2018-1-of-4-/manifest.json",
              "type": "Manifest"
            }
          ]
        },
        "selector": {
          "type": "RangeSelector",
          "t": "3.0,62.0"
        }
      }
    },
    {
      "@context": "http://www.w3.org/ns/anno.jsonld",
      "id": "interview-with-bebe-mille-2018-1-of-4--canvas-1-gesel-mason-annotation-1.json",
      "type": "Annotation",
      "motivation": [
        "supplementing",
        "commenting"
      ],
      "body": {
        "type": "TextualBody",
        "value": "Because I think initially I created this project because growing up in high school the two options I was given were, oh, Dance Theatre of Harlem or Alvin Ailey, and I was like, \"I don't do either one of those things,\" but I was like, \"but you know, there are other African American choreographers who are doing work that maybe folks would be interested in and I'm interested in,\" and I wanted audiences to know about. So, there was also this old conversation about black dance, which was also-",
        "format": "text/plain",
        "purpose": "commenting"
      },
      "target": {
        "source": {
          "id": "https://makenziepeacock.github.io/NoBoundaries/interview-with-bebe-mille-2018-1-of-4-/canvas-1/canvas",
          "type": "Canvas",
          "partOf": [
            {
              "id": "https://makenziepeacock.github.io/NoBoundaries/interview-with-bebe-mille-2018-1-of-4-/manifest.json",
              "type": "Manifest"
            }
          ]
        },
        "selector": {
          "type": "RangeSelector",
          "t": "62.0,104.0"
        }
      }
    },
    {
      "@context": "http://www.w3.org/ns/anno.jsonld",
      "id": "interview-with-bebe-mille-2018-1-of-4--canvas-1-gesel-mason-annotation-2.json",
      "type": "Annotation",
      "motivation": [
        "supplementing",
        "commenting"
      ],
      "body": {
        "type": "TextualBody",
        "value": "Yeah.",
        "format": "text/plain",
        "purpose": "commenting"
      },
      "target": {
        "source": {
          "id": "https://makenziepeacock.github.io/NoBoundaries/interview-with-bebe-mille-2018-1-of-4-/canvas-1/canvas",
          "type": "Canvas",
          "partOf": [
            {
              "id": "https://makenziepeacock.github.io/NoBoundaries/interview-with-bebe-mille-2018-1-of-4-/manifest.json",
              "type": "Manifest"
            }
          ]
        },
        "selector": {
          "type": "PointSelector",
          "t": "108.0"
        }
      }
    },
    {
      "@context": "http://www.w3.org/ns/anno.jsonld",
      "id": "interview-with-bebe-mille-2018-1-of-4--canvas-1-gesel-mason-annotation-3.json",
      "type": "Annotation",
      "motivation": [
        "supplementing",
        "commenting"
      ],
      "body": {
        "type": "TextualBody",
        "value": "That's what was interesting about doing it again in 2014, was this idea of like ... well one, students hadn't heard of this, they hadn't really heard of black dance as a term. It's like, \"Really? Great!\"",
        "format": "text/plain",
        "purpose": "commenting"
      },
      "target": {
        "source": {
          "id": "https://makenziepeacock.github.io/NoBoundaries/interview-with-bebe-mille-2018-1-of-4-/canvas-1/canvas",
          "type": "Canvas",
          "partOf": [
            {
              "id": "https://makenziepeacock.github.io/NoBoundaries/interview-with-bebe-mille-2018-1-of-4-/manifest.json",
              "type": "Manifest"
            }
          ]
        },
        "selector": {
          "type": "RangeSelector",
          "t": "109.0,123.0"
        }
      }
    },
    {
      "@context": "http://www.w3.org/ns/anno.jsonld",
      "id": "interview-with-bebe-mille-2018-1-of-4--canvas-1-gesel-mason-annotation-4.json",
      "type": "Annotation",
      "motivation": [
        "supplementing",
        "commenting"
      ],
      "body": {
        "type": "TextualBody",
        "value": "And at the same time I was like, \"But do you know who some of these folks are and how we got here?\" So this question about legacy has shown up and I feel totally differently about ... instead of pushing away, about trying to build a bridge between the past and the present.",
        "format": "text/plain",
        "purpose": "commenting"
      },
      "target": {
        "source": {
          "id": "https://makenziepeacock.github.io/NoBoundaries/interview-with-bebe-mille-2018-1-of-4-/canvas-1/canvas",
          "type": "Canvas",
          "partOf": [
            {
              "id": "https://makenziepeacock.github.io/NoBoundaries/interview-with-bebe-mille-2018-1-of-4-/manifest.json",
              "type": "Manifest"
            }
          ]
        },
        "selector": {
          "type": "RangeSelector",
          "t": "128.0,151.0"
        }
      }
    },
    {
      "@context": "http://www.w3.org/ns/anno.jsonld",
      "id": "interview-with-bebe-mille-2018-1-of-4--canvas-1-gesel-mason-annotation-5.json",
      "type": "Annotation",
      "motivation": [
        "supplementing",
        "commenting"
      ],
      "body": {
        "type": "TextualBody",
        "value": "Well, I think that-",
        "format": "text/plain",
        "purpose": "commenting"
      },
      "target": {
        "source": {
          "id": "https://makenziepeacock.github.io/NoBoundaries/interview-with-bebe-mille-2018-1-of-4-/canvas-1/canvas",
          "type": "Canvas",
          "partOf": [
            {
              "id": "https://makenziepeacock.github.io/NoBoundaries/interview-with-bebe-mille-2018-1-of-4-/manifest.json",
              "type": "Manifest"
            }
          ]
        },
        "selector": {
          "type": "RangeSelector",
          "t": "401.0,403.0"
        }
      }
    },
    {
      "@context": "http://www.w3.org/ns/anno.jsonld",
      "id": "interview-with-bebe-mille-2018-1-of-4--canvas-1-gesel-mason-annotation-6.json",
      "type": "Annotation",
      "motivation": [
        "supplementing",
        "commenting"
      ],
      "body": {
        "type": "TextualBody",
        "value": "I'm going to grab some water. I've become aware of the, \"Boom, boom, boom, boom,\" outside of ...",
        "format": "text/plain",
        "purpose": "commenting"
      },
      "target": {
        "source": {
          "id": "https://makenziepeacock.github.io/NoBoundaries/interview-with-bebe-mille-2018-1-of-4-/canvas-1/canvas",
          "type": "Canvas",
          "partOf": [
            {
              "id": "https://makenziepeacock.github.io/NoBoundaries/interview-with-bebe-mille-2018-1-of-4-/manifest.json",
              "type": "Manifest"
            }
          ]
        },
        "selector": {
          "type": "RangeSelector",
          "t": "412.0,419.0"
        }
      }
    }
  ]
}