{
  "@context": "http://iiif.io/api/presentation/3/context.json",
  "id": "https://makenziepeacock.github.io/NoBoundaries/annotations/interview-with-gesel-mason-2014--canvas-1-daniel-beahm.json",
  "type": "AnnotationPage",
  "label": "Daniel Beahm",
  "items": [
    {
      "@context": "http://www.w3.org/ns/anno.jsonld",
      "id": "interview-with-gesel-mason-2014--canvas-1-daniel-beahm-annotation-0.json",
      "type": "Annotation",
      "motivation": [
        "supplementing",
        "commenting"
      ],
      "body": [
        {
          "type": "TextualBody",
          "value": "Okay. So, what are you doing? I mean why are you still working on this project 10 years later? If it's something that you started 10 years ago and that you did 10 years ago, why is it still happening?",
          "format": "text/plain",
          "purpose": "commenting"
        },
        {
          "type": "TextualBody",
          "value": "Daniel Beahm",
          "format": "text/plain",
          "purpose": "tagging"
        }
      ],
      "target": {
        "source": {
          "id": "https://makenziepeacock.github.io/NoBoundaries/interview-with-gesel-mason-2014-/canvas-1/canvas",
          "type": "Canvas",
          "partOf": [
            {
              "id": "https://makenziepeacock.github.io/NoBoundaries/interview-with-gesel-mason-2014-/manifest.json",
              "type": "Manifest"
            }
          ]
        },
        "selector": {
          "type": "RangeSelector",
          "t": "14.0,30.0"
        }
      }
    },
    {
      "@context": "http://www.w3.org/ns/anno.jsonld",
      "id": "interview-with-gesel-mason-2014--canvas-1-daniel-beahm-annotation-1.json",
      "type": "Annotation",
      "motivation": [
        "supplementing",
        "commenting"
      ],
      "body": [
        {
          "type": "TextualBody",
          "value": "Okay. Do you want me to sit ... Would it be easier if I sat over there-",
          "format": "text/plain",
          "purpose": "commenting"
        },
        {
          "type": "TextualBody",
          "value": "Daniel Beahm",
          "format": "text/plain",
          "purpose": "tagging"
        }
      ],
      "target": {
        "source": {
          "id": "https://makenziepeacock.github.io/NoBoundaries/interview-with-gesel-mason-2014-/canvas-1/canvas",
          "type": "Canvas",
          "partOf": [
            {
              "id": "https://makenziepeacock.github.io/NoBoundaries/interview-with-gesel-mason-2014-/manifest.json",
              "type": "Manifest"
            }
          ]
        },
        "selector": {
          "type": "RangeSelector",
          "t": "382.0,386.0"
        }
      }
    },
    {
      "@context": "http://www.w3.org/ns/anno.jsonld",
      "id": "interview-with-gesel-mason-2014--canvas-1-daniel-beahm-annotation-2.json",
      "type": "Annotation",
      "motivation": [
        "supplementing",
        "commenting"
      ],
      "body": [
        {
          "type": "TextualBody",
          "value": "... so it doesn't feel like there's somebody sitting in the room and you're talking [inaudible 00:06:28].",
          "format": "text/plain",
          "purpose": "commenting"
        },
        {
          "type": "TextualBody",
          "value": "Daniel Beahm",
          "format": "text/plain",
          "purpose": "tagging"
        }
      ],
      "target": {
        "source": {
          "id": "https://makenziepeacock.github.io/NoBoundaries/interview-with-gesel-mason-2014-/canvas-1/canvas",
          "type": "Canvas",
          "partOf": [
            {
              "id": "https://makenziepeacock.github.io/NoBoundaries/interview-with-gesel-mason-2014-/manifest.json",
              "type": "Manifest"
            }
          ]
        },
        "selector": {
          "type": "RangeSelector",
          "t": "386.0,389.0"
        }
      }
    },
    {
      "@context": "http://www.w3.org/ns/anno.jsonld",
      "id": "interview-with-gesel-mason-2014--canvas-1-daniel-beahm-annotation-3.json",
      "type": "Annotation",
      "motivation": [
        "supplementing",
        "commenting"
      ],
      "body": [
        {
          "type": "TextualBody",
          "value": "Yep. Exactly. Tell me about this video that you're making.",
          "format": "text/plain",
          "purpose": "commenting"
        },
        {
          "type": "TextualBody",
          "value": "Daniel Beahm",
          "format": "text/plain",
          "purpose": "tagging"
        }
      ],
      "target": {
        "source": {
          "id": "https://makenziepeacock.github.io/NoBoundaries/interview-with-gesel-mason-2014-/canvas-1/canvas",
          "type": "Canvas",
          "partOf": [
            {
              "id": "https://makenziepeacock.github.io/NoBoundaries/interview-with-gesel-mason-2014-/manifest.json",
              "type": "Manifest"
            }
          ]
        },
        "selector": {
          "type": "RangeSelector",
          "t": "401.0,420.0"
        }
      }
    },
    {
      "@context": "http://www.w3.org/ns/anno.jsonld",
      "id": "interview-with-gesel-mason-2014--canvas-1-daniel-beahm-annotation-4.json",
      "type": "Annotation",
      "motivation": [
        "supplementing",
        "commenting"
      ],
      "body": [
        {
          "type": "TextualBody",
          "value": "You know what, this is a really good shot. Do you mind if I change the camera angle on this, and then you'll have something to cut back and forth between?",
          "format": "text/plain",
          "purpose": "commenting"
        },
        {
          "type": "TextualBody",
          "value": "Daniel Beahm",
          "format": "text/plain",
          "purpose": "tagging"
        }
      ],
      "target": {
        "source": {
          "id": "https://makenziepeacock.github.io/NoBoundaries/interview-with-gesel-mason-2014-/canvas-1/canvas",
          "type": "Canvas",
          "partOf": [
            {
              "id": "https://makenziepeacock.github.io/NoBoundaries/interview-with-gesel-mason-2014-/manifest.json",
              "type": "Manifest"
            }
          ]
        },
        "selector": {
          "type": "RangeSelector",
          "t": "434.0,439.0"
        }
      }
    },
    {
      "@context": "http://www.w3.org/ns/anno.jsonld",
      "id": "interview-with-gesel-mason-2014--canvas-1-daniel-beahm-annotation-5.json",
      "type": "Annotation",
      "motivation": [
        "supplementing",
        "commenting"
      ],
      "body": [
        {
          "type": "TextualBody",
          "value": "Because this is actually [inaudible 00:07:21]. Sorry. I don't want to interrupt your flow, but I think it'll make it visually more interesting.",
          "format": "text/plain",
          "purpose": "commenting"
        },
        {
          "type": "TextualBody",
          "value": "Daniel Beahm",
          "format": "text/plain",
          "purpose": "tagging"
        }
      ],
      "target": {
        "source": {
          "id": "https://makenziepeacock.github.io/NoBoundaries/interview-with-gesel-mason-2014-/canvas-1/canvas",
          "type": "Canvas",
          "partOf": [
            {
              "id": "https://makenziepeacock.github.io/NoBoundaries/interview-with-gesel-mason-2014-/manifest.json",
              "type": "Manifest"
            }
          ]
        },
        "selector": {
          "type": "RangeSelector",
          "t": "440.0,447.0"
        }
      }
    },
    {
      "@context": "http://www.w3.org/ns/anno.jsonld",
      "id": "interview-with-gesel-mason-2014--canvas-1-daniel-beahm-annotation-6.json",
      "type": "Annotation",
      "motivation": [
        "supplementing",
        "commenting"
      ],
      "body": [
        {
          "type": "TextualBody",
          "value": "No. It's nice to have you looking sort of into the ...",
          "format": "text/plain",
          "purpose": "commenting"
        },
        {
          "type": "TextualBody",
          "value": "Daniel Beahm",
          "format": "text/plain",
          "purpose": "tagging"
        }
      ],
      "target": {
        "source": {
          "id": "https://makenziepeacock.github.io/NoBoundaries/interview-with-gesel-mason-2014-/canvas-1/canvas",
          "type": "Canvas",
          "partOf": [
            {
              "id": "https://makenziepeacock.github.io/NoBoundaries/interview-with-gesel-mason-2014-/manifest.json",
              "type": "Manifest"
            }
          ]
        },
        "selector": {
          "type": "RangeSelector",
          "t": "470.0,473.0"
        }
      }
    },
    {
      "@context": "http://www.w3.org/ns/anno.jsonld",
      "id": "interview-with-gesel-mason-2014--canvas-1-daniel-beahm-annotation-7.json",
      "type": "Annotation",
      "motivation": [
        "supplementing",
        "commenting"
      ],
      "body": [
        {
          "type": "TextualBody",
          "value": "So, I'm gonna put this to [inaudible 00:07:56] ... I gotta back up a little bit because I'm too close to you.",
          "format": "text/plain",
          "purpose": "commenting"
        },
        {
          "type": "TextualBody",
          "value": "Daniel Beahm",
          "format": "text/plain",
          "purpose": "tagging"
        }
      ],
      "target": {
        "source": {
          "id": "https://makenziepeacock.github.io/NoBoundaries/interview-with-gesel-mason-2014-/canvas-1/canvas",
          "type": "Canvas",
          "partOf": [
            {
              "id": "https://makenziepeacock.github.io/NoBoundaries/interview-with-gesel-mason-2014-/manifest.json",
              "type": "Manifest"
            }
          ]
        },
        "selector": {
          "type": "RangeSelector",
          "t": "473.0,480.0"
        }
      }
    },
    {
      "@context": "http://www.w3.org/ns/anno.jsonld",
      "id": "interview-with-gesel-mason-2014--canvas-1-daniel-beahm-annotation-8.json",
      "type": "Annotation",
      "motivation": [
        "supplementing",
        "commenting"
      ],
      "body": [
        {
          "type": "TextualBody",
          "value": "I know.",
          "format": "text/plain",
          "purpose": "commenting"
        },
        {
          "type": "TextualBody",
          "value": "Daniel Beahm",
          "format": "text/plain",
          "purpose": "tagging"
        }
      ],
      "target": {
        "source": {
          "id": "https://makenziepeacock.github.io/NoBoundaries/interview-with-gesel-mason-2014-/canvas-1/canvas",
          "type": "Canvas",
          "partOf": [
            {
              "id": "https://makenziepeacock.github.io/NoBoundaries/interview-with-gesel-mason-2014-/manifest.json",
              "type": "Manifest"
            }
          ]
        },
        "selector": {
          "type": "RangeSelector",
          "t": "482.0,485.0"
        }
      }
    },
    {
      "@context": "http://www.w3.org/ns/anno.jsonld",
      "id": "interview-with-gesel-mason-2014--canvas-1-daniel-beahm-annotation-9.json",
      "type": "Annotation",
      "motivation": [
        "supplementing",
        "commenting"
      ],
      "body": [
        {
          "type": "TextualBody",
          "value": "I've got a phone on me. Hold on a second. It is 2:51.",
          "format": "text/plain",
          "purpose": "commenting"
        },
        {
          "type": "TextualBody",
          "value": "Daniel Beahm",
          "format": "text/plain",
          "purpose": "tagging"
        }
      ],
      "target": {
        "source": {
          "id": "https://makenziepeacock.github.io/NoBoundaries/interview-with-gesel-mason-2014-/canvas-1/canvas",
          "type": "Canvas",
          "partOf": [
            {
              "id": "https://makenziepeacock.github.io/NoBoundaries/interview-with-gesel-mason-2014-/manifest.json",
              "type": "Manifest"
            }
          ]
        },
        "selector": {
          "type": "RangeSelector",
          "t": "486.0,496.0"
        }
      }
    },
    {
      "@context": "http://www.w3.org/ns/anno.jsonld",
      "id": "interview-with-gesel-mason-2014--canvas-1-daniel-beahm-annotation-10.json",
      "type": "Annotation",
      "motivation": [
        "supplementing",
        "commenting"
      ],
      "body": [
        {
          "type": "TextualBody",
          "value": "So, I think I'll have you still ... If you want to address me this way, I think that'll look good. Yeah. All right [inaudible 00:08:45]. Good. All right, we're rolling again. [inaudible 00:09:10] ask you the question about the video again?",
          "format": "text/plain",
          "purpose": "commenting"
        },
        {
          "type": "TextualBody",
          "value": "Daniel Beahm",
          "format": "text/plain",
          "purpose": "tagging"
        }
      ],
      "target": {
        "source": {
          "id": "https://makenziepeacock.github.io/NoBoundaries/interview-with-gesel-mason-2014-/canvas-1/canvas",
          "type": "Canvas",
          "partOf": [
            {
              "id": "https://makenziepeacock.github.io/NoBoundaries/interview-with-gesel-mason-2014-/manifest.json",
              "type": "Manifest"
            }
          ]
        },
        "selector": {
          "type": "RangeSelector",
          "t": "510.0,560.0"
        }
      }
    },
    {
      "@context": "http://www.w3.org/ns/anno.jsonld",
      "id": "interview-with-gesel-mason-2014--canvas-1-daniel-beahm-annotation-11.json",
      "type": "Annotation",
      "motivation": [
        "supplementing",
        "commenting"
      ],
      "body": [
        {
          "type": "TextualBody",
          "value": "Cool.",
          "format": "text/plain",
          "purpose": "commenting"
        },
        {
          "type": "TextualBody",
          "value": "Daniel Beahm",
          "format": "text/plain",
          "purpose": "tagging"
        }
      ],
      "target": {
        "source": {
          "id": "https://makenziepeacock.github.io/NoBoundaries/interview-with-gesel-mason-2014-/canvas-1/canvas",
          "type": "Canvas",
          "partOf": [
            {
              "id": "https://makenziepeacock.github.io/NoBoundaries/interview-with-gesel-mason-2014-/manifest.json",
              "type": "Manifest"
            }
          ]
        },
        "selector": {
          "type": "RangeSelector",
          "t": "699.0,701.0"
        }
      }
    },
    {
      "@context": "http://www.w3.org/ns/anno.jsonld",
      "id": "interview-with-gesel-mason-2014--canvas-1-daniel-beahm-annotation-12.json",
      "type": "Annotation",
      "motivation": [
        "supplementing",
        "commenting"
      ],
      "body": [
        {
          "type": "TextualBody",
          "value": "You got some really cool stuff in there.",
          "format": "text/plain",
          "purpose": "commenting"
        },
        {
          "type": "TextualBody",
          "value": "Daniel Beahm",
          "format": "text/plain",
          "purpose": "tagging"
        }
      ],
      "target": {
        "source": {
          "id": "https://makenziepeacock.github.io/NoBoundaries/interview-with-gesel-mason-2014-/canvas-1/canvas",
          "type": "Canvas",
          "partOf": [
            {
              "id": "https://makenziepeacock.github.io/NoBoundaries/interview-with-gesel-mason-2014-/manifest.json",
              "type": "Manifest"
            }
          ]
        },
        "selector": {
          "type": "RangeSelector",
          "t": "709.0,710.0"
        }
      }
    },
    {
      "@context": "http://www.w3.org/ns/anno.jsonld",
      "id": "interview-with-gesel-mason-2014--canvas-1-daniel-beahm-annotation-13.json",
      "type": "Annotation",
      "motivation": [
        "supplementing",
        "commenting"
      ],
      "body": [
        {
          "type": "TextualBody",
          "value": "Mm-hmm (affirmative). Sure.",
          "format": "text/plain",
          "purpose": "commenting"
        },
        {
          "type": "TextualBody",
          "value": "Daniel Beahm",
          "format": "text/plain",
          "purpose": "tagging"
        }
      ],
      "target": {
        "source": {
          "id": "https://makenziepeacock.github.io/NoBoundaries/interview-with-gesel-mason-2014-/canvas-1/canvas",
          "type": "Canvas",
          "partOf": [
            {
              "id": "https://makenziepeacock.github.io/NoBoundaries/interview-with-gesel-mason-2014-/manifest.json",
              "type": "Manifest"
            }
          ]
        },
        "selector": {
          "type": "RangeSelector",
          "t": "733.0,736.0"
        }
      }
    },
    {
      "@context": "http://www.w3.org/ns/anno.jsonld",
      "id": "interview-with-gesel-mason-2014--canvas-1-daniel-beahm-annotation-14.json",
      "type": "Annotation",
      "motivation": [
        "supplementing",
        "commenting"
      ],
      "body": [
        {
          "type": "TextualBody",
          "value": "Yeah, she had questions about that, too. I assume all of this footage can ...",
          "format": "text/plain",
          "purpose": "commenting"
        },
        {
          "type": "TextualBody",
          "value": "Daniel Beahm",
          "format": "text/plain",
          "purpose": "tagging"
        }
      ],
      "target": {
        "source": {
          "id": "https://makenziepeacock.github.io/NoBoundaries/interview-with-gesel-mason-2014-/canvas-1/canvas",
          "type": "Canvas",
          "partOf": [
            {
              "id": "https://makenziepeacock.github.io/NoBoundaries/interview-with-gesel-mason-2014-/manifest.json",
              "type": "Manifest"
            }
          ]
        },
        "selector": {
          "type": "RangeSelector",
          "t": "740.0,745.0"
        }
      }
    },
    {
      "@context": "http://www.w3.org/ns/anno.jsonld",
      "id": "interview-with-gesel-mason-2014--canvas-1-daniel-beahm-annotation-15.json",
      "type": "Annotation",
      "motivation": [
        "supplementing",
        "commenting"
      ],
      "body": [
        {
          "type": "TextualBody",
          "value": "... go for either thing.",
          "format": "text/plain",
          "purpose": "commenting"
        },
        {
          "type": "TextualBody",
          "value": "Daniel Beahm",
          "format": "text/plain",
          "purpose": "tagging"
        }
      ],
      "target": {
        "source": {
          "id": "https://makenziepeacock.github.io/NoBoundaries/interview-with-gesel-mason-2014-/canvas-1/canvas",
          "type": "Canvas",
          "partOf": [
            {
              "id": "https://makenziepeacock.github.io/NoBoundaries/interview-with-gesel-mason-2014-/manifest.json",
              "type": "Manifest"
            }
          ]
        },
        "selector": {
          "type": "RangeSelector",
          "t": "745.0,746.0"
        }
      }
    },
    {
      "@context": "http://www.w3.org/ns/anno.jsonld",
      "id": "interview-with-gesel-mason-2014--canvas-1-daniel-beahm-annotation-16.json",
      "type": "Annotation",
      "motivation": [
        "supplementing",
        "commenting"
      ],
      "body": [
        {
          "type": "TextualBody",
          "value": "Okay.",
          "format": "text/plain",
          "purpose": "commenting"
        },
        {
          "type": "TextualBody",
          "value": "Daniel Beahm",
          "format": "text/plain",
          "purpose": "tagging"
        }
      ],
      "target": {
        "source": {
          "id": "https://makenziepeacock.github.io/NoBoundaries/interview-with-gesel-mason-2014-/canvas-1/canvas",
          "type": "Canvas",
          "partOf": [
            {
              "id": "https://makenziepeacock.github.io/NoBoundaries/interview-with-gesel-mason-2014-/manifest.json",
              "type": "Manifest"
            }
          ]
        },
        "selector": {
          "type": "PointSelector",
          "t": "751.0"
        }
      }
    },
    {
      "@context": "http://www.w3.org/ns/anno.jsonld",
      "id": "interview-with-gesel-mason-2014--canvas-1-daniel-beahm-annotation-17.json",
      "type": "Annotation",
      "motivation": [
        "supplementing",
        "commenting"
      ],
      "body": [
        {
          "type": "TextualBody",
          "value": "Yeah. Absolutely.",
          "format": "text/plain",
          "purpose": "commenting"
        },
        {
          "type": "TextualBody",
          "value": "Daniel Beahm",
          "format": "text/plain",
          "purpose": "tagging"
        }
      ],
      "target": {
        "source": {
          "id": "https://makenziepeacock.github.io/NoBoundaries/interview-with-gesel-mason-2014-/canvas-1/canvas",
          "type": "Canvas",
          "partOf": [
            {
              "id": "https://makenziepeacock.github.io/NoBoundaries/interview-with-gesel-mason-2014-/manifest.json",
              "type": "Manifest"
            }
          ]
        },
        "selector": {
          "type": "RangeSelector",
          "t": "754.0,755.0"
        }
      }
    }
  ]
}