{
  "@context": "http://iiif.io/api/presentation/3/context.json",
  "id": "https://makenziepeacock.github.io/NoBoundaries/annotations/jumping-the-broom-canvas-1-description-.json",
  "type": "AnnotationPage",
  "label": "Description ",
  "items": [
    {
      "@context": "http://www.w3.org/ns/anno.jsonld",
      "id": "jumping-the-broom-canvas-1-description--annotation-0.json",
      "type": "Annotation",
      "motivation": [
        "supplementing",
        "commenting"
      ],
      "body": [
        {
          "type": "TextualBody",
          "value": "The performer begins to slowly turn her head to left, eyebrows furrowing, and her face beginning to scrunch together with frustration and fear. ",
          "format": "text/plain",
          "purpose": "commenting"
        },
        {
          "type": "TextualBody",
          "value": "Performance",
          "format": "text/plain",
          "purpose": "tagging"
        },
        {
          "type": "TextualBody",
          "value": "David Rousséve",
          "format": "text/plain",
          "purpose": "tagging"
        },
        {
          "type": "TextualBody",
          "value": "Gesel Mason",
          "format": "text/plain",
          "purpose": "tagging"
        },
        {
          "type": "TextualBody",
          "value": "Jumping the Broom",
          "format": "text/plain",
          "purpose": "tagging"
        },
        {
          "type": "TextualBody",
          "value": "No Boundaries Performance 2018",
          "format": "text/plain",
          "purpose": "tagging"
        }
      ],
      "target": {
        "source": {
          "id": "https://makenziepeacock.github.io/NoBoundaries/jumping-the-broom/canvas-1/canvas",
          "type": "Canvas",
          "partOf": [
            {
              "id": "https://makenziepeacock.github.io/NoBoundaries/jumping-the-broom/manifest.json",
              "type": "Manifest"
            }
          ]
        },
        "selector": {
          "type": "RangeSelector",
          "t": "91.0,101.0"
        }
      }
    }
  ]
}